CHANGES.rst
MANIFEST.in
README.rst
setup.cfg
setup.py
docs/INSTALL.txt
docs/LICENSE.GPL
docs/LICENSE.txt
src/plone/__init__.py
src/plone.mls.core.egg-info/PKG-INFO
src/plone.mls.core.egg-info/SOURCES.txt
src/plone.mls.core.egg-info/dependency_links.txt
src/plone.mls.core.egg-info/entry_points.txt
src/plone.mls.core.egg-info/namespace_packages.txt
src/plone.mls.core.egg-info/not-zip-safe
src/plone.mls.core.egg-info/requires.txt
src/plone.mls.core.egg-info/top_level.txt
src/plone/mls/__init__.py
src/plone/mls/core/__init__.py
src/plone/mls/core/api.py
src/plone/mls/core/config.py
src/plone/mls/core/configure.zcml
src/plone/mls/core/i18n.py
src/plone/mls/core/interfaces.py
src/plone/mls/core/migration.py
src/plone/mls/core/navigation.py
src/plone/mls/core/permissions.zcml
src/plone/mls/core/profiles.zcml
src/plone/mls/core/setuphandlers.py
src/plone/mls/core/testing.py
src/plone/mls/core/utils.py
src/plone/mls/core/browser/__init__.py
src/plone/mls/core/browser/configure.zcml
src/plone/mls/core/browser/controlpanel.py
src/plone/mls/core/browser/interfaces.py
src/plone/mls/core/browser/localconfig.py
src/plone/mls/core/browser/resources/icon.png
src/plone/mls/core/browser/resources/plone_mls_core.js
src/plone/mls/core/locales/manual.pot
src/plone/mls/core/locales/plone.mls.core.pot
src/plone/mls/core/locales/ar/LC_MESSAGES/plone.mls.core.po
src/plone/mls/core/locales/cmn/LC_MESSAGES/plone.mls.core.po
src/plone/mls/core/locales/de/LC_MESSAGES/plone.mls.core.po
src/plone/mls/core/locales/en/LC_MESSAGES/plone.mls.core.po
src/plone/mls/core/locales/es/LC_MESSAGES/plone.mls.core.po
src/plone/mls/core/locales/et/LC_MESSAGES/plone.mls.core.po
src/plone/mls/core/locales/fr/LC_MESSAGES/plone.mls.core.po
src/plone/mls/core/locales/it/LC_MESSAGES/plone.mls.core.po
src/plone/mls/core/locales/ja/LC_MESSAGES/plone.mls.core.po
src/plone/mls/core/locales/pt/LC_MESSAGES/plone.mls.core.po
src/plone/mls/core/locales/ru/LC_MESSAGES/plone.mls.core.po
src/plone/mls/core/locales/vi/LC_MESSAGES/plone.mls.core.po
src/plone/mls/core/locales/vi_VN/LC_MESSAGES/plone.mls.core.po
src/plone/mls/core/locales/zh/LC_MESSAGES/plone.mls.core.po
src/plone/mls/core/locales/zh_TW/LC_MESSAGES/plone.mls.core.po
src/plone/mls/core/profiles/base/metadata.xml
src/plone/mls/core/profiles/plone4/actions.xml
